zendir/__init__.py
zendir/connection/__init__.py
zendir/connection/client.py
zendir/data/__init__.py
zendir/data/frame.py
zendir/http/__init__.py
zendir/http/rqst.py
zendir/maths/__init__.py
zendir/maths/astro.py
zendir/maths/computer_library.py
zendir/maths/constants.py
zendir/maths/constellations.py
zendir/maths/data.py
zendir/maths/kinematics.py
zendir/maths/mass.py
zendir/maths/sensors.py
zendir/maths/utils.py
zendir/mqtt/__init__.py
zendir/mqtt/client.py
zendir/simulation/__init__.py
zendir/simulation/behaviour.py
zendir/simulation/context.py
zendir/simulation/instance.py
zendir/simulation/message.py
zendir/simulation/model.py
zendir/simulation/object.py
zendir/simulation/simulation.py
zendir/simulation/system.py
zendir/utils/__init__.py
zendir/utils/exception.py
zendir/utils/helper.py
zendir/utils/printer.py
zendir/utils/runner.py
zendir-1.4.1.0.dist-info/licenses/LICENSE
zendir-1.4.1.0.dist-info/METADATA
zendir-1.4.1.0.dist-info/WHEEL
zendir-1.4.1.0.dist-info/top_level.txt
zendir-1.4.1.0.dist-info/RECORD
